task3/counter.sv
module counter #(
  parameter WIDTH = 8
)(
  // interface signals
  input  logic             clk,      // clock
  input  logic             rst,      // reset
  input  logic             ld,       // load counter from data
  input  logic [WIDTH-1:0] v,        // value to preload
  output logic [WIDTH-1:0] count     // count output
);

always_ff @ (posedge clk) begin
  if (rst) 
    count <= {WIDTH{1'b0}};           // Reset the counter to 0
  else 
    count <= ld ? v : count + {{WIDTH-1{1'b0}}, 1'b1}; // Load or increment the counter
end

endmodule  // This is the correct way to end the module

task3/counter.vcd
$version Generated by VerilatedVcd $end
$date Sat Oct 19 15:38:35 2024 $end
$timescale 1ps $end

 $scope module TOP $end
  $var wire  1 # clk $end
  $var wire  8 ' count [7:0] $end
  $var wire  1 % ld $end
  $var wire  1 $ rst $end
  $var wire  8 & v [7:0] $end
  $scope module counter $end
   $var wire 32 ( WIDTH [31:0] $end
   $var wire  1 # clk $end
   $var wire  8 ' count [7:0] $end
   $var wire  1 % ld $end
   $var wire  1 $ rst $end
   $var wire  8 & v [7:0] $end
  $upscope $end
 $upscope $end
$enddefinitions $end


#0
1#
1$
0%
b00000000 &
b00000000 '
b00000000000000000000000000001000 (
#1
0#
#2
1#
1%
b00111101 &
#3
0#
#4
1#
#5
0#
#6
1#
0$
#7
0#
#8
1#
b00111101 '
#9
0#
#10
1#
#11
0#
#12
1#
#13
0#
#14
1#
#15
0#
#16
1#
#17
0#
#18
1#
#19
0#
#20
1#
#21
0#
#22
1#
#23
0#
#24
1#
#25
0#
#26
1#
#27
0#
#28
1#
#29
0#
#30
1#
#31
0#
#32
1#
1$
#33
0#
#34
1#
0$
b00000000 '
#35
0#
#36
1#
b00111101 '
#37
0#
#38
1#
#39
0#
#40
1#
#41
0#
#42
1#
#43
0#
#44
1#
#45
0#
#46
1#
#47
0#
#48
1#
#49
0#
#50
1#
#51
0#
#52
1#
#53
0#
#54
1#
#55
0#
#56
1#
#57
0#
#58
1#
#59
0#
#60
1#
#61
0#
#62
1#
#63
0#
#64
1#
#65
0#
#66
1#
#67
0#
#68
1#
#69
0#
#70
1#
#71
0#
#72
1#
#73
0#
#74
1#
#75
0#
#76
1#
#77
0#
#78
1#
#79
0#
#80
1#
#81
0#
#82
1#
#83
0#
#84
1#
#85
0#
#86
1#
#87
0#
#88
1#
#89
0#
#90
1#
#91
0#
#92
1#
#93
0#
#94
1#
#95
0#
#96
1#
#97
0#
#98
1#
#99
0#
#100
1#
#101
0#
#102
1#
#103
0#
#104
1#
#105
0#
#106
1#
#107
0#
#108
1#
#109
0#
#110
1#
#111
0#
#112
1#
#113
0#
#114
1#
#115
0#
#116
1#
#117
0#
#118
1#
#119
0#
#120
1#
#121
0#
#122
1#
#123
0#
#124
1#
#125
0#
#126
1#
#127
0#
#128
1#
#129
0#
#130
1#
#131
0#
#132
1#
#133
0#
#134
1#
#135
0#
#136
1#
0%
#137
0#
#138
1#
b00111110 '
#139
0#
#140
1#
b00111111 '
#141
0#
#142
1#
b01000000 '
#143
0#
#144
1#
b01000001 '
#145
0#
#146
1#
b01000010 '
#147
0#
#148
1#
b01000011 '
#149
0#
#150
1#
b01000100 '
#151
0#
#152
1#
b01000101 '
#153
0#
#154
1#
b01000110 '
#155
0#
#156
1#
b01000111 '
#157
0#
#158
1#
b01001000 '
#159
0#
#160
1#
b01001001 '
#161
0#
#162
1#
b01001010 '
#163
0#
#164
1#
b01001011 '
#165
0#
#166
1#
b01001100 '
#167
0#
#168
1#
b01001101 '
#169
0#
#170
1#
b01001110 '
#171
0#
#172
1#
b01001111 '
#173
0#
#174
1#
b01010000 '
#175
0#
#176
1#
b01010001 '
#177
0#
#178
1#
b01010010 '
#179
0#
#180
1#
b01010011 '
#181
0#
#182
1#
b01010100 '
#183
0#
#184
1#
b01010101 '
#185
0#
#186
1#
b01010110 '
#187
0#
#188
1#
b01010111 '
#189
0#
#190
1#
b01011000 '
#191
0#
#192
1#
b01011001 '
#193
0#
#194
1#
b01011010 '
#195
0#
#196
1#
b01011011 '
#197
0#
#198
1#
b01011100 '
#199
0#
#200
1#
b01011101 '
#201
0#
#202
1#
b01011110 '
#203
0#
#204
1#
b01011111 '
#205
0#
#206
1#
b01100000 '
#207
0#
#208
1#
b01100001 '
#209
0#
#210
1#
b01100010 '
#211
0#
#212
1#
b01100011 '
#213
0#
#214
1#
b01100100 '
#215
0#
#216
1#
b01100101 '
#217
0#
#218
1#
b01100110 '
#219
0#
#220
1#
b01100111 '
#221
0#
#222
1#
b01101000 '
#223
0#
#224
1#
b01101001 '
#225
0#
#226
1#
b01101010 '
#227
0#
#228
1#
b01101011 '
#229
0#
#230
1#
b01101100 '
#231
0#
#232
1#
b01101101 '
#233
0#
#234
1#
b01101110 '
#235
0#
#236
1#
b01101111 '
#237
0#
#238
1#
1%
b01110000 '
#239
0#
#240
1#
b00111101 '
